lsbranch/__init__.py
lsbranch/cli.py
lsbranch/lsbranch.py
lsbranch-1.0.2.dist-info/LICENSE.txt
lsbranch-1.0.2.dist-info/METADATA
lsbranch-1.0.2.dist-info/RECORD
lsbranch-1.0.2.dist-info/WHEEL
lsbranch-1.0.2.dist-info/entry_points.txt
lsbranch-1.0.2.dist-info/top_level.txt
