Metadata-Version: 2.1
Name: lsbranch
Version: 1.0.2
Summary: List all directories with .git subdirectory and show current branch for each.
Home-page: https://github.com/arrrlo/lsbranch
Author: Ivan Arar
Author-email: ivan.arar@gmail.com
License: MIT
Project-URL: Source, https://github.com/arrrlo/lsbranch
Keywords: git,branch,ls
Platform: UNKNOWN
Classifier: Development Status :: 4 - Beta
Classifier: Intended Audience :: Developers
Classifier: Topic :: Software Development :: Build Tools
Classifier: License :: OSI Approved :: MIT License
Classifier: Programming Language :: Python :: 2.7
Classifier: Programming Language :: Python :: 3.6
Requires-Dist: click (==6.3)
Requires-Dist: colorama (~=0.3)
Requires-Dist: pyfiglet (~=0.7.5)
Requires-Dist: termcolor (~=1.1.0)
